ssb_project_cli/__init__.py
ssb_project_cli/__main__.py
ssb_project_cli/py.typed
ssb_project_cli/ssb_project/__init__.py
ssb_project_cli/ssb_project/app.py
ssb_project_cli/ssb_project/build/__init__.py
ssb_project_cli/ssb_project/build/build.py
ssb_project_cli/ssb_project/build/environment.py
ssb_project_cli/ssb_project/build/poetry.py
ssb_project_cli/ssb_project/build/prompt.py
ssb_project_cli/ssb_project/build/temp_template_repo.py
ssb_project_cli/ssb_project/build_cmds.md
ssb_project_cli/ssb_project/clean/__init__.py
ssb_project_cli/ssb_project/clean/clean.py
ssb_project_cli/ssb_project/create/__init__.py
ssb_project_cli/ssb_project/create/create.py
ssb_project_cli/ssb_project/create/github.py
ssb_project_cli/ssb_project/create/local_repo.py
ssb_project_cli/ssb_project/create/prompt.py
ssb_project_cli/ssb_project/create/repo_privacy.py
ssb_project_cli/ssb_project/create/temp_git_repo.py
ssb_project_cli/ssb_project/settings.py
ssb_project_cli/ssb_project/util.py
ssb_project_cli-1.7.2.dist-info/LICENSE
ssb_project_cli-1.7.2.dist-info/METADATA
ssb_project_cli-1.7.2.dist-info/WHEEL
ssb_project_cli-1.7.2.dist-info/entry_points.txt
ssb_project_cli-1.7.2.dist-info/RECORD
