Metadata-Version: 2.3
Name: ssb-project-cli
Version: 1.7.2
Summary: SSB Project CLI
License: MIT
Author: Statistics Norway
Author-email: stat-dev@ssb.no
Requires-Python: >=3.10
Classifier: Development Status :: 4 - Beta
Classifier: License :: OSI Approved :: MIT License
Classifier: Programming Language :: Python :: 3
Classifier: Programming Language :: Python :: 3.10
Classifier: Programming Language :: Python :: 3.11
Classifier: Programming Language :: Python :: 3.12
Classifier: Programming Language :: Python :: 3.13
Requires-Dist: cruft (>=2.11.1)
Requires-Dist: gitpython (>=3.1.27)
Requires-Dist: ipykernel (>=6.25.2)
Requires-Dist: jupyter-client (>=8.3.1)
Requires-Dist: kvakk-git-tools (>=2.5.1)
Requires-Dist: poetry (>=2.0)
Requires-Dist: psutil (>=5.9.4)
Requires-Dist: pygithub (>=1.55)
Requires-Dist: questionary (>=1.10.0)
Requires-Dist: requests (>=2.32.3)
Requires-Dist: rich (>=12.5.1)
Requires-Dist: tomli (>=2.0.1)
Requires-Dist: typer (==0.19.2)
Project-URL: Changelog, https://github.com/statisticsnorway/ssb-project-cli/releases
Project-URL: Documentation, https://ssb-project-cli.readthedocs.io
Project-URL: Homepage, https://github.com/statisticsnorway/ssb-project-cli
Project-URL: Repository, https://github.com/statisticsnorway/ssb-project-cli
